mcp_s3_server/__init__.py
mcp_s3_server/config.py
mcp_s3_server/server_main.py
mcp_s3_server/tools/__init__.py
mcp_s3_server/tools/list_buckets_tool.py
mcp_s3_server/tools/list_object_tool.py
mcp_s3_server/utils/__init__.py
mcp_s3_server/utils/utils.py
mcp_s3_server-0.1.3.dist-info/METADATA
mcp_s3_server-0.1.3.dist-info/WHEEL
mcp_s3_server-0.1.3.dist-info/entry_points.txt
mcp_s3_server-0.1.3.dist-info/RECORD
