Metadata-Version: 2.4
Name: mcp-s3-server
Version: 0.1.3
Summary: An implementation of a Model Context Protocol (MCP) server for AWS S3, enabling AI models, particularly Large Language Models (LLMs), to securely interact with S3 buckets.
Project-URL: Homepage, https://github.com/ENGRZULQARNAIN/mcp_server_s3_download_files
Project-URL: Repository, https://github.com/ENGRZULQARNAIN/mcp_server_s3_download_files
Project-URL: Issues, https://github.com/ENGRZULQARNAIN/mcp_server_s3_download_files/issues
Author-email: ZULQARNAIN <zulqar4791@gmail.com>
License: MIT
Keywords: ai,aws,llm,mcp,s3
Classifier: Development Status :: 3 - Alpha
Classifier: Intended Audience :: Developers
Classifier: License :: OSI Approved :: MIT License
Classifier: Programming Language :: Python :: 3
Classifier: Programming Language :: Python :: 3.10
Classifier: Programming Language :: Python :: 3.11
Classifier: Programming Language :: Python :: 3.12
Classifier: Programming Language :: Python :: 3.13
Requires-Python: >=3.10
Requires-Dist: aioboto3>=15.1.0
Requires-Dist: anyio>=4.10.0
Requires-Dist: mcp>=1.13.1
Requires-Dist: python-dotenv>=1.1.1
